<?xml version="1.0" encoding="ISO-8859-1" ?>

<!DOCTYPE tiles-definitions PUBLIC
"-//Apache Software Foundation//DTD Tiles Configuration 1.1//EN"
"http://jakarta.apache.org/struts/dtds/tiles-config_1_1.dtd">

<tiles-definitions>
  <!--templates-->
  <definition name="layout.template" path="/layout.jsp">
    <put name="pageName" value=""/>
    <put name="title" value="InterMine" />
    <put name="header" value="/header.jsp"/>
    <put name="menu" value="/menu.jsp"/>
    <put name="errorMessages" value="/errorMessages.jsp"/>
    <put name="description" value="/description.jsp"/>
    <put name="footer" value="/footer.jsp"/>
    <put name="body" value=""/>
  </definition>
  <!--pages-->
  <definition name="login.page" extends="layout.template">
    <put name="body" value="login.jsp"/>
    <put name="pageName" value="login"/>
  </definition>
  <definition name="query.page" extends="layout.template">
    <put name="body" value="query.tile"/>
    <put name="pageName" value="query"/>
  </definition>
  <definition name="iqlQuery.page" extends="layout.template">
    <put name="body" value="iqlQuery.tile"/>
    <put name="pageName" value="iqlquery"/>
  </definition>
  <definition name="history.page" extends="layout.template">
    <put name="body" value="history.tile"/>
    <put name="pageName" value="history"/>
  </definition>
  <definition name="begin.page" extends="layout.template">
    <put name="body" value="begin.tile"/>
    <put name="pageName" value="begin"/>
  </definition>
  <definition name="template.page" extends="layout.template">
    <put name="body" value="template.tile"/>
    <put name="pageName" value="template"/>
  </definition>
  <definition name="templates.page" extends="layout.template">
    <put name="body" value="templates.tile"/>
    <put name="pageName" value="templates"/>
  </definition>
  <definition name="templateBuilder.page" extends="layout.template">
    <put name="body" value="templateBuilder.tile"/>
    <put name="pageName" value="templateBuilder"/>
  </definition>
  <definition name="examples.page" extends="layout.template">
    <put name="body" value="examples.jsp"/>
    <put name="pageName" value="examples"/>
  </definition>
  <definition name="bagBuild.page" extends="layout.template">
    <put name="body" value="bagBuild.tile"/>
    <put name="pageName" value="bagBuild"/>
  </definition>
  <definition name="help.page" extends="layout.template">
    <put name="body" value="help.jsp"/>
    <put name="pageName" value="help"/>
  </definition>
  <definition name="feedback.page" extends="layout.template">
    <put name="body" value="feedback.jsp"/>
    <put name="pageName" value="feedback"/>
  </definition>
  <definition name="classChooser.page" extends="layout.template">
    <put name="body" value="queryClassSelect.jsp"/>
    <put name="pageName" value="classChooser"/>
  </definition>
  <definition name="results.page" extends="layout.template">
    <put name="body" value="table.jsp"/>
    <put name="pageName" value="results"/>
  </definition>
  <definition name="error.page" extends="layout.template">
    <put name="body" value="error.jsp"/>
    <put name="pageName" value="error"/>
  </definition>
  <definition name="objectDetails.page" extends="layout.template">
    <put name="body" value="objectDetailsPage.tile"/>
    <put name="pageName" value="objectDetails"/>
  </definition>
  <definition name="collectionDetails.page" extends="layout.template">
    <put name="body" value="collectionDetailsPage.tile"/>
    <put name="pageName" value="collectionDetails"/>
  </definition>
  <definition name="bagDetails.page" extends="layout.template">
    <put name="body" value="bagDetailsPage.tile"/>
    <put name="pageName" value="bagDetails"/>
  </definition>
  <definition name="documentation.page" extends="layout.template">
    <put name="body" value="docbook.jsp"/>
    <put name="pageName" value="documentation"/>
  </definition>
  <definition name="tree.page" extends="layout.template">
    <put name="body" value="tree.tile"/>
    <put name="pageName" value="tree"/>
  </definition>
  <definition name="classDescription.page" extends="layout.template">
    <put name="body" value="classDescription.tile"/>
    <put name="pageName" value="classDescription"/>
  </definition>
  <!--tiles-->
  <definition name="classDescription.tile" path="/classDescription.jsp" controllerUrl="/initClassDescription.do"/>
  <definition name="begin.tile" path="/begin.jsp" controllerUrl="/initBegin.do">
    <put name="usertemplates" value="templateList.jsp"/>
    <put name="globaltemplates" value="templateList.jsp"/>
  </definition>
  <definition name="export.tile" path="/export.jsp" controllerUrl="/initExport.do"/>
  <definition name="query.tile" path="/query.jsp">
    <put name="main" value="main.tile"/>
    <put name="view" value="view.tile"/>
  </definition>
  <definition name="main.tile" path="/main.jsp" controllerUrl="/initMain.do"/>
  <definition name="view.tile" path="/view.jsp">
    <put name="saveQuery" value="/saveQuery.jsp"/>
    <put name="createTemplate" value="/createTemplate.jsp"/>
  </definition> 
  <definition name="iqlQuery.tile" path="/iqlQuery.jsp" controllerUrl="/initIqlQuery.do"/>
  <definition name="history.tile" path="/history.jsp">
    <put name="historyBagView" value="historyBagView.jsp"/>
    <put name="historyQueryView" value="historyQueryView.jsp"/>
  </definition>
  <definition name="objectView.tile" path="/objectView.jsp" controllerUrl="/initObjectView.do"/>
  <definition name="objectDetailsPage.tile" path="/objectDetails.jsp" controllerUrl="/initObjectDetails.do"/>
  <definition name="collectionDetailsPage.tile" path="/table.jsp" controllerUrl="/initCollectionDetails.do"/>
  <definition name="bagDetailsPage.tile" path="/table.jsp" controllerUrl="/initBagDetails.do"/>
  <definition name="tree.tile" path="/tree.jsp" controllerUrl="/initTree.do"/>
  <definition name="bagBuild.tile" path="/bagBuild.jsp" controllerUrl="/initBagBuild.do"/>
  <definition name="template.tile" path="/template.jsp" controllerUrl="/initTemplate.do"/>
  <definition name="templates.tile" path="/templates.jsp" controllerUrl="/initTemplates.do"/>
  <definition name="templateBuilder.tile" path="/templateBuilder.jsp" controllerUrl="/initTemplateBuilder.do">
    <put name="preview" value="template.tile"/>
  </definition>
</tiles-definitions>
